README.md
setup.py
Lvt_Evaluation.egg-info/PKG-INFO
Lvt_Evaluation.egg-info/SOURCES.txt
Lvt_Evaluation.egg-info/dependency_links.txt
Lvt_Evaluation.egg-info/requires.txt
Lvt_Evaluation.egg-info/top_level.txt
lvt_eval/__init__.py
lvt_eval/evaluation/__init__.py
lvt_eval/evaluation/coco_json_eval.py
lvt_eval/evaluation/from_studio_json_eval.py
lvt_eval/tools/__init__.py
lvt_eval/tools/ap_per_class.py
lvt_eval/tools/cal_new_ap.py
lvt_eval/tools/cal_precision_and_recall.py
lvt_eval/tools/cal_pred_error.py
lvt_eval/tools/coco_error_analyze.py
lvt_eval/tools/coco_evaluator.py
lvt_eval/tools/customcoco.py
lvt_eval/tools/customcocoeval.py
lvt_eval/utils/__init__.py
lvt_eval/utils/boxes.py
lvt_eval/utils/check_predictions.py
lvt_eval/utils/draw_boxes.py
lvt_eval/utils/functions.py
lvt_eval/utils/general.py
lvt_eval/utils/gt_handler.py
lvt_eval/utils/save_excel.py
lvt_eval/utils/sorted_image_id.py