Metadata-Version: 2.1
Name: Lvt-Evaluation
Version: 0.1.0
Summary: Lvt evaluation of image object detection.
Home-page: 
Author: JiajiaLiao, KeleiJiang
Author-email: jiajialiao_08@163.com
License: MIT
Classifier: License :: OSI Approved :: MIT License
Classifier: Programming Language :: Python
Classifier: Programming Language :: Python :: 3
Classifier: Programming Language :: Python :: 3.8
Classifier: Programming Language :: Python :: Implementation :: CPython
Classifier: Programming Language :: Python :: Implementation :: PyPy
Requires-Python: >=3.8
